pyalgos/__init__.py
pyalgos/__pkg__.py
pyalgos/sorting/__init__.py
pyalgos/sorting/insertion.py
pyalgos/sorting/merge.py
pyalgos/sorting/selection.py
pyalgos-0.1.2.dist-info/DESCRIPTION.rst
pyalgos-0.1.2.dist-info/METADATA
pyalgos-0.1.2.dist-info/RECORD
pyalgos-0.1.2.dist-info/WHEEL
pyalgos-0.1.2.dist-info/metadata.json
pyalgos-0.1.2.dist-info/top_level.txt
