Metadata-Version: 2.0
Name: pyalgos
Version: 0.1.2
Summary: UNKNOWN
Home-page: https://github.com/bharadwajyarlagadda/pyalgos
Author: Bharadwaj Yarlagadda
Author-email: yarlagaddabharadwaj@gmail.com
License: MIT License
Keywords: algorithms sorting insertion selection
Platform: UNKNOWN
Classifier: Development Status :: 2 - Pre-Alpha
Classifier: Intended Audience :: Developers
Classifier: Operating System :: OS Independent
Classifier: Programming Language :: Python
Classifier: License :: OSI Approved :: MIT License
Classifier: Topic :: Software Development :: Libraries
Classifier: Topic :: Software Development :: Libraries :: Python Modules
Classifier: Programming Language :: Python
Classifier: Programming Language :: Python :: 2
Classifier: Programming Language :: Python :: 2.7
Classifier: Programming Language :: Python :: 3
Classifier: Programming Language :: Python :: 3.3
Classifier: Programming Language :: Python :: 3.4
Classifier: Programming Language :: Python :: 3.5
